apiclient/__init__.py
apiclient/api.py
apiclient/py.typed
apiclient/types.py
apiclient/backends/__init__.py
apiclient/backends/_aiohttp.py
apiclient/backends/_httpx.py
aio_apiclient-1.7.0.dist-info/LICENSE
aio_apiclient-1.7.0.dist-info/METADATA
aio_apiclient-1.7.0.dist-info/WHEEL
aio_apiclient-1.7.0.dist-info/top_level.txt
aio_apiclient-1.7.0.dist-info/RECORD
