Metadata-Version: 2.1
Name: aio-apiclient
Version: 1.7.0
Summary: Async helper to work with HTTP APIs
Home-page: https://github.com/klen/aio-apiclient
Author: Kirill Klenov
Author-email: horneds@gmail.com
License: MIT
Project-URL: Documentation, https://github.com/klen/aio-apiclient
Project-URL: Source code, https://github.com/klen/aio-apiclient
Project-URL: Issue tracker, https://github.com/klen/aio-apiclient/issues
Keywords: apiclient,muffin,asyncio,trio,curio
Classifier: Development Status :: 5 - Production/Stable
Classifier: Intended Audience :: Developers
Classifier: License :: OSI Approved :: MIT License
Classifier: Programming Language :: Python
Classifier: Programming Language :: Python :: 3
Classifier: Programming Language :: Python :: 3.7
Classifier: Programming Language :: Python :: 3.8
Classifier: Programming Language :: Python :: 3.9
Classifier: Programming Language :: Python :: 3.10
Classifier: Framework :: AsyncIO
Classifier: Framework :: Trio
Requires-Python: >=3.7
License-File: LICENSE
Provides-Extra: aiohttp
Requires-Dist: aiohttp ; extra == 'aiohttp'
Provides-Extra: httpx
Requires-Dist: httpx (>=0.20.0) ; extra == 'httpx'
Provides-Extra: tests
Requires-Dist: aiohttp ; extra == 'tests'
Requires-Dist: httpx ; extra == 'tests'
Requires-Dist: pytest ; extra == 'tests'
Requires-Dist: pytest-aio[curio,trio] (>=1.5.0) ; extra == 'tests'
Requires-Dist: pytest-mypy ; extra == 'tests'
Requires-Dist: types-setuptools ; extra == 'tests'
Requires-Dist: mock ; (python_version < "3.8") and extra == 'tests'
Requires-Dist: typing-extensions ; (python_version < "3.8") and extra == 'tests'
